design.sv
// Code your design here
// Code your design here
module mult_4x4(reset,start,A,B,O,Finish);
input reset,start;
input[3:0] A,B; 
output [7:0] O;
output Finish;
reg [7:0] O;
wire Finish;  
wire Phi0,Phi1;// 2 phase clocking
wire m1,m2,m3,m4;
// state machine
reg[3:0] State;
// Accumulator
reg [8:0] ACC; // Accumulator
// logic to create 2 phase clocking when starting
nand u0(m1,start,m2);
buf #20 u1(m2,m1);
buf #10 u2(Phi0,m1);// First phase clocking
not #2 u5(m4,Phi0);
assign m3=~m1; 
and #2 u4(Phi1,m3,m4);// Second phase clocking
assign Finish = (State==9)? 1'b1:1'b0; // Finish Flag
// FSM
always @(posedge Phi0 or posedge Phi1 or posedge reset)
begin
 if(reset) begin
 State <= 0; 
 ACC <= 0; 
 O <= 0; 
 end
 else if((Phi0==1'b1) || (Phi1==1'b1)) begin // 2 phase clocking
 if(State==0)
 begin
 ACC[8:4] <= 5'b00000; // begin cycle
 ACC[3:0] <= A; // Load A
 State <= 1;
 end
 else if(State==1 || State == 3 || State ==5 || State ==7) 
                // add/shift State
 begin
 if(ACC[0] == 1'b1) begin // add multiplicand
 ACC[8:4] <= {1'b0,ACC[7:4]} + B; 
 State <= State + 1;
 end
 else
 begin
 ACC <= {1'b0,ACC[8:1]};// shift right
 State <= State + 2;
 end
 end
 else if(State==2 || State == 4 || State ==6 || State ==8) 
                // shift State
 begin
 ACC <= {1'b0,ACC[8:1]}; // shift right
 State <= State + 1;
 end 
 else if(State == 9) begin
 State <= 0;
 O <= ACC[7:0]; 
 end
 end
end 
endmodule

testbench.sv
// Code your testbench here
// or browse Examples
// Code your testbench here
// or browse Examples
module test();
// signals
reg start,reset;
reg[3:0] A,B;
// Outputs
wire [7:0] O;
wire Finish;
// device under test
  mult_4x4 uut(reset,start, A,B,O,Finish);
initial begin
reset=1; // reset
#40 start = 0;A =14; B= 11;
#400 reset = 0; 
#40 start = 1; // start
//@(posedge Finish);
//start = 0;
//$finish;
end 
initial
begin
  $dumpfile("dump.vcd");
  $dumpvars;
  #10000;
  $finish;
end

endmodule

dump.vcd
$date
	Fri Jun 18 17:19:38 2021
$end
$version
	Icarus Verilog
$end
$timescale
	1s
$end
$scope module test $end
$var wire 1 ! Finish $end
$var wire 8 " O [7:0] $end
$var reg 4 # A [3:0] $end
$var reg 4 $ B [3:0] $end
$var reg 1 % reset $end
$var reg 1 & start $end
$scope module uut $end
$var wire 4 ' A [3:0] $end
$var wire 4 ( B [3:0] $end
$var wire 1 ! Finish $end
$var wire 1 ) Phi0 $end
$var wire 1 * Phi1 $end
$var wire 1 + m1 $end
$var wire 1 , m2 $end
$var wire 1 - m3 $end
$var wire 1 . m4 $end
$var wire 1 / reset $end
$var wire 1 0 start $end
$var reg 9 1 ACC [8:0] $end
$var reg 8 2 O [7:0] $end
$var reg 4 3 State [3:0] $end
$upscope $end
$upscope $end
$enddefinitions $end
#0
$dumpvars
b0 3
b0 2
b0 1
x0
1/
x.
x-
x,
x+
x*
x)
bx (
bx '
x&
1%
bx $
bx #
b0 "
0!
$end
#40
0-
1+
b1011 $
b1011 (
b1110 #
b1110 '
0&
00
#42
0*
#50
1)
#52
0.
#60
1,
#440
0%
0/
#480
1-
0+
1&
10
#490
0)
#492
1.
#494
b1 3
b1110 1
1*
#500
0-
1+
0,
#502
0*
#510
b11 3
b111 1
1)
#512
0.
#520
1-
0+
1,
#530
0)
#532
1.
#534
b100 3
b10110111 1
1*
#540
0-
1+
0,
#542
0*
#550
b101 3
b1011011 1
1)
#552
0.
#560
1-
0+
1,
#570
0)
#572
1.
#574
b110 3
b100001011 1
1*
#580
0-
1+
0,
#582
0*
#590
b111 3
b10000101 1
1)
#592
0.
#600
1-
0+
1,
#610
0)
#612
1.
#614
b1000 3
b100110101 1
1*
#620
0-
1+
0,
#622
0*
#630
1!
b1001 3
b10011010 1
1)
#632
0.
#640
1-
0+
1,
#650
0)
#652
1.
#654
0!
b10011010 2
b10011010 "
b0 3
1*
#660
0-
1+
0,
#662
0*
#670
b1 3
b1110 1
1)
#672
0.
#680
1-
0+
1,
#690
0)
#692
1.
#694
b11 3
b111 1
1*
#700
0-
1+
0,
#702
0*
#710
b100 3
b10110111 1
1)
#712
0.
#720
1-
0+
1,
#730
0)
#732
1.
#734
b101 3
b1011011 1
1*
#740
0-
1+
0,
#742
0*
#750
b110 3
b100001011 1
1)
#752
0.
#760
1-
0+
1,
#770
0)
#772
1.
#774
b111 3
b10000101 1
1*
#780
0-
1+
0,
#782
0*
#790
b1000 3
b100110101 1
1)
#792
0.
#800
1-
0+
1,
#810
0)
#812
1.
#814
1!
b1001 3
b10011010 1
1*
#820
0-
1+
0,
#822
0*
#830
0!
b0 3
1)
#832
0.
#840
1-
0+
1,
#850
0)
#852
1.
#854
b1 3
b1110 1
1*
#860
0-
1+
0,
#862
0*
#870
b11 3
b111 1
1)
#872
0.
#880
1-
0+
1,
#890
0)
#892
1.
#894
b100 3
b10110111 1
1*
#900
0-
1+
0,
#902
0*
#910
b101 3
b1011011 1
1)
#912
0.
#920
1-
0+
1,
#930
0)
#932
1.
#934
b110 3
b100001011 1
1*
#940
0-
1+
0,
#942
0*
#950
b111 3
b10000101 1
1)
#952
0.
#960
1-
0+
1,
#970
0)
#972
1.
#974
b1000 3
b100110101 1
1*
#980
0-
1+
0,
#982
0*
#990
1!
b1001 3
b10011010 1
1)
#992
0.
#1000
1-
0+
1,
#1010
0)
#1012
1.
#1014
0!
b0 3
1*
#1020
0-
1+
0,
#1022
0*
#1030
b1 3
b1110 1
1)
#1032
0.
#1040
1-
0+
1,
#1050
0)
#1052
1.
#1054
b11 3
b111 1
1*
#1060
0-
1+
0,
#1062
0*
#1070
b100 3
b10110111 1
1)
#1072
0.
#1080
1-
0+
1,
#1090
0)
#1092
1.
#1094
b101 3
b1011011 1
1*
#1100
0-
1+
0,
#1102
0*
#1110
b110 3
b100001011 1
1)
#1112
0.
#1120
1-
0+
1,
#1130
0)
#1132
1.
#1134
b111 3
b10000101 1
1*
#1140
0-
1+
0,
#1142
0*
#1150
b1000 3
b100110101 1
1)
#1152
0.
#1160
1-
0+
1,
#1170
0)
#1172
1.
#1174
1!
b1001 3
b10011010 1
1*
#1180
0-
1+
0,
#1182
0*
#1190
0!
b0 3
1)
#1192
0.
#1200
1-
0+
1,
#1210
0)
#1212
1.
#1214
b1 3
b1110 1
1*
#1220
0-
1+
0,
#1222
0*
#1230
b11 3
b111 1
1)
#1232
0.
#1240
1-
0+
1,
#1250
0)
#1252
1.
#1254
b100 3
b10110111 1
1*
#1260
0-
1+
0,
#1262
0*
#1270
b101 3
b1011011 1
1)
#1272
0.
#1280
1-
0+
1,
#1290
0)
#1292
1.
#1294
b110 3
b100001011 1
1*
#1300
0-
1+
0,
#1302
0*
#1310
b111 3
b10000101 1
1)
#1312
0.
#1320
1-
0+
1,
#1330
0)
#1332
1.
#1334
b1000 3
b100110101 1
1*
#1340
0-
1+
0,
#1342
0*
#1350
1!
b1001 3
b10011010 1
1)
#1352
0.
#1360
1-
0+
1,
#1370
0)
#1372
1.
#1374
0!
b0 3
1*
#1380
0-
1+
0,
#1382
0*
#1390
b1 3
b1110 1
1)
#1392
0.
#1400
1-
0+
1,
#1410
0)
#1412
1.
#1414
b11 3
b111 1
1*
#1420
0-
1+
0,
#1422
0*
#1430
b100 3
b10110111 1
1)
#1432
0.
#1440
1-
0+
1,
#1450
0)
#1452
1.
#1454
b101 3
b1011011 1
1*
#1460
0-
1+
0,
#1462
0*
#1470
b110 3
b100001011 1
1)
#1472
0.
#1480
1-
0+
1,
#1490
0)
#1492
1.
#1494
b111 3
b10000101 1
1*
#1500
0-
1+
0,
#1502
0*
#1510
b1000 3
b100110101 1
1)
#1512
0.
#1520
1-
0+
1,
#1530
0)
#1532
1.
#1534
1!
b1001 3
b10011010 1
1*
#1540
0-
1+
0,
#1542
0*
#1550
0!
b0 3
1)
#1552
0.
#1560
1-
0+
1,
#1570
0)
#1572
1.
#1574
b1 3
b1110 1
1*
#1580
0-
1+
0,
#1582
0*
#1590
b11 3
b111 1
1)
#1592
0.
#1600
1-
0+
1,
#1610
0)
#1612
1.
#1614
b100 3
b10110111 1
1*
#1620
0-
1+
0,
#1622
0*
#1630
b101 3
b1011011 1
1)
#1632
0.
#1640
1-
0+
1,
#1650
0)
#1652
1.
#1654
b110 3
b100001011 1
1*
#1660
0-
1+
0,
#1662
0*
#1670
b111 3
b10000101 1
1)
#1672
0.
#1680
1-
0+
1,
#1690
0)
#1692
1.
#1694
b1000 3
b100110101 1
1*
#1700
0-
1+
0,
#1702
0*
#1710
1!
b1001 3
b10011010 1
1)
#1712
0.
#1720
1-
0+
1,
#1730
0)
#1732
1.
#1734
0!
b0 3
1*
#1740
0-
1+
0,
#1742
0*
#1750
b1 3
b1110 1
1)
#1752
0.
#1760
1-
0+
1,
#1770
0)
#1772
1.
#1774
b11 3
b111 1
1*
#1780
0-
1+
0,
#1782
0*
#1790
b100 3
b10110111 1
1)
#1792
0.
#1800
1-
0+
1,
#1810
0)
#1812
1.
#1814
b101 3
b1011011 1
1*
#1820
0-
1+
0,
#1822
0*
#1830
b110 3
b100001011 1
1)
#1832
0.
#1840
1-
0+
1,
#1850
0)
#1852
1.
#1854
b111 3
b10000101 1
1*
#1860
0-
1+
0,
#1862
0*
#1870
b1000 3
b100110101 1
1)
#1872
0.
#1880
1-
0+
1,
#1890
0)
#1892
1.
#1894
1!
b1001 3
b10011010 1
1*
#1900
0-
1+
0,
#1902
0*
#1910
0!
b0 3
1)
#1912
0.
#1920
1-
0+
1,
#1930
0)
#1932
1.
#1934
b1 3
b1110 1
1*
#1940
0-
1+
0,
#1942
0*
#1950
b11 3
b111 1
1)
#1952
0.
#1960
1-
0+
1,
#1970
0)
#1972
1.
#1974
b100 3
b10110111 1
1*
#1980
0-
1+
0,
#1982
0*
#1990
b101 3
b1011011 1
1)
#1992
0.
#2000
1-
0+
1,
#2010
0)
#2012
1.
#2014
b110 3
b100001011 1
1*
#2020
0-
1+
0,
#2022
0*
#2030
b111 3
b10000101 1
1)
#2032
0.
#2040
1-
0+
1,
#2050
0)
#2052
1.
#2054
b1000 3
b100110101 1
1*
#2060
0-
1+
0,
#2062
0*
#2070
1!
b1001 3
b10011010 1
1)
#2072
0.
#2080
1-
0+
1,
#2090
0)
#2092
1.
#2094
0!
b0 3
1*
#2100
0-
1+
0,
#2102
0*
#2110
b1 3
b1110 1
1)
#2112
0.
#2120
1-
0+
1,
#2130
0)
#2132
1.
#2134
b11 3
b111 1
1*
#2140
0-
1+
0,
#2142
0*
#2150
b100 3
b10110111 1
1)
#2152
0.
#2160
1-
0+
1,
#2170
0)
#2172
1.
#2174
b101 3
b1011011 1
1*
#2180
0-
1+
0,
#2182
0*
#2190
b110 3
b100001011 1
1)
#2192
0.
#2200
1-
0+
1,
#2210
0)
#2212
1.
#2214
b111 3
b10000101 1
1*
#2220
0-
1+
0,
#2222
0*
#2230
b1000 3
b100110101 1
1)
#2232
0.
#2240
1-
0+
1,
#2250
0)
#2252
1.
#2254
1!
b1001 3
b10011010 1
1*
#2260
0-
1+
0,
#2262
0*
#2270
0!
b0 3
1)
#2272
0.
#2280
1-
0+
1,
#2290
0)
#2292
1.
#2294
b1 3
b1110 1
1*
#2300
0-
1+
0,
#2302
0*
#2310
b11 3
b111 1
1)
#2312
0.
#2320
1-
0+
1,
#2330
0)
#2332
1.
#2334
b100 3
b10110111 1
1*
#2340
0-
1+
0,
#2342
0*
#2350
b101 3
b1011011 1
1)
#2352
0.
#2360
1-
0+
1,
#2370
0)
#2372
1.
#2374
b110 3
b100001011 1
1*
#2380
0-
1+
0,
#2382
0*
#2390
b111 3
b10000101 1
1)
#2392
0.
#2400
1-
0+
1,
#2410
0)
#2412
1.
#2414
b1000 3
b100110101 1
1*
#2420
0-
1+
0,
#2422
0*
#2430
1!
b1001 3
b10011010 1
1)
#2432
0.
#2440
1-
0+
1,
#2450
0)
#2452
1.
#2454
0!
b0 3
1*
#2460
0-
1+
0,
#2462
0*
#2470
b1 3
b1110 1
1)
#2472
0.
#2480
1-
0+
1,
#2490
0)
#2492
1.
#2494
b11 3
b111 1
1*
#2500
0-
1+
0,
#2502
0*
#2510
b100 3
b10110111 1
1)
#2512
0.
#2520
1-
0+
1,
#2530
0)
#2532
1.
#2534
b101 3
b1011011 1
1*
#2540
0-
1+
0,
#2542
0*
#2550
b110 3
b100001011 1
1)
#2552
0.
#2560
1-
0+
1,
#2570
0)
#2572
1.
#2574
b111 3
b10000101 1
1*
#2580
0-
1+
0,
#2582
0*
#2590
b1000 3
b100110101 1
1)
#2592
0.
#2600
1-
0+
1,
#2610
0)
#2612
1.
#2614
1!
b1001 3
b10011010 1
1*
#2620
0-
1+
0,
#2622
0*
#2630
0!
b0 3
1)
#2632
0.
#2640
1-
0+
1,
#2650
0)
#2652
1.
#2654
b1 3
b1110 1
1*
#2660
0-
1+
0,
#2662
0*
#2670
b11 3
b111 1
1)
#2672
0.
#2680
1-
0+
1,
#2690
0)
#2692
1.
#2694
b100 3
b10110111 1
1*
#2700
0-
1+
0,
#2702
0*
#2710
b101 3
b1011011 1
1)
#2712
0.
#2720
1-
0+
1,
#2730
0)
#2732
1.
#2734
b110 3
b100001011 1
1*
#2740
0-
1+
0,
#2742
0*
#2750
b111 3
b10000101 1
1)
#2752
0.
#2760
1-
0+
1,
#2770
0)
#2772
1.
#2774
b1000 3
b100110101 1
1*
#2780
0-
1+
0,
#2782
0*
#2790
1!
b1001 3
b10011010 1
1)
#2792
0.
#2800
1-
0+
1,
#2810
0)
#2812
1.
#2814
0!
b0 3
1*
#2820
0-
1+
0,
#2822
0*
#2830
b1 3
b1110 1
1)
#2832
0.
#2840
1-
0+
1,
#2850
0)
#2852
1.
#2854
b11 3
b111 1
1*
#2860
0-
1+
0,
#2862
0*
#2870
b100 3
b10110111 1
1)
#2872
0.
#2880
1-
0+
1,
#2890
0)
#2892
1.
#2894
b101 3
b1011011 1
1*
#2900
0-
1+
0,
#2902
0*
#2910
b110 3
b100001011 1
1)
#2912
0.
#2920
1-
0+
1,
#2930
0)
#2932
1.
#2934
b111 3
b10000101 1
1*
#2940
0-
1+
0,
#2942
0*
#2950
b1000 3
b100110101 1
1)
#2952
0.
#2960
1-
0+
1,
#2970
0)
#2972
1.
#2974
1!
b1001 3
b10011010 1
1*
#2980
0-
1+
0,
#2982
0*
#2990
0!
b0 3
1)
#2992
0.
#3000
1-
0+
1,
#3010
0)
#3012
1.
#3014
b1 3
b1110 1
1*
#3020
0-
1+
0,
#3022
0*
#3030
b11 3
b111 1
1)
#3032
0.
#3040
1-
0+
1,
#3050
0)
#3052
1.
#3054
b100 3
b10110111 1
1*
#3060
0-
1+
0,
#3062
0*
#3070
b101 3
b1011011 1
1)
#3072
0.
#3080
1-
0+
1,
#3090
0)
#3092
1.
#3094
b110 3
b100001011 1
1*
#3100
0-
1+
0,
#3102
0*
#3110
b111 3
b10000101 1
1)
#3112
0.
#3120
1-
0+
1,
#3130
0)
#3132
1.
#3134
b1000 3
b100110101 1
1*
#3140
0-
1+
0,
#3142
0*
#3150
1!
b1001 3
b10011010 1
1)
#3152
0.
#3160
1-
0+
1,
#3170
0)
#3172
1.
#3174
0!
b0 3
1*
#3180
0-
1+
0,
#3182
0*
#3190
b1 3
b1110 1
1)
#3192
0.
#3200
1-
0+
1,
#3210
0)
#3212
1.
#3214
b11 3
b111 1
1*
#3220
0-
1+
0,
#3222
0*
#3230
b100 3
b10110111 1
1)
#3232
0.
#3240
1-
0+
1,
#3250
0)
#3252
1.
#3254
b101 3
b1011011 1
1*
#3260
0-
1+
0,
#3262
0*
#3270
b110 3
b100001011 1
1)
#3272
0.
#3280
1-
0+
1,
#3290
0)
#3292
1.
#3294
b111 3
b10000101 1
1*
#3300
0-
1+
0,
#3302
0*
#3310
b1000 3
b100110101 1
1)
#3312
0.
#3320
1-
0+
1,
#3330
0)
#3332
1.
#3334
1!
b1001 3
b10011010 1
1*
#3340
0-
1+
0,
#3342
0*
#3350
0!
b0 3
1)
#3352
0.
#3360
1-
0+
1,
#3370
0)
#3372
1.
#3374
b1 3
b1110 1
1*
#3380
0-
1+
0,
#3382
0*
#3390
b11 3
b111 1
1)
#3392
0.
#3400
1-
0+
1,
#3410
0)
#3412
1.
#3414
b100 3
b10110111 1
1*
#3420
0-
1+
0,
#3422
0*
#3430
b101 3
b1011011 1
1)
#3432
0.
#3440
1-
0+
1,
#3450
0)
#3452
1.
#3454
b110 3
b100001011 1
1*
#3460
0-
1+
0,
#3462
0*
#3470
b111 3
b10000101 1
1)
#3472
0.
#3480
1-
0+
1,
#3490
0)
#3492
1.
#3494
b1000 3
b100110101 1
1*
#3500
0-
1+
0,
#3502
0*
#3510
1!
b1001 3
b10011010 1
1)
#3512
0.
#3520
1-
0+
1,
#3530
0)
#3532
1.
#3534
0!
b0 3
1*
#3540
0-
1+
0,
#3542
0*
#3550
b1 3
b1110 1
1)
#3552
0.
#3560
1-
0+
1,
#3570
0)
#3572
1.
#3574
b11 3
b111 1
1*
#3580
0-
1+
0,
#3582
0*
#3590
b100 3
b10110111 1
1)
#3592
0.
#3600
1-
0+
1,
#3610
0)
#3612
1.
#3614
b101 3
b1011011 1
1*
#3620
0-
1+
0,
#3622
0*
#3630
b110 3
b100001011 1
1)
#3632
0.
#3640
1-
0+
1,
#3650
0)
#3652
1.
#3654
b111 3
b10000101 1
1*
#3660
0-
1+
0,
#3662
0*
#3670
b1000 3
b100110101 1
1)
#3672
0.
#3680
1-
0+
1,
#3690
0)
#3692
1.
#3694
1!
b1001 3
b10011010 1
1*
#3700
0-
1+
0,
#3702
0*
#3710
0!
b0 3
1)
#3712
0.
#3720
1-
0+
1,
#3730
0)
#3732
1.
#3734
b1 3
b1110 1
1*
#3740
0-
1+
0,
#3742
0*
#3750
b11 3
b111 1
1)
#3752
0.
#3760
1-
0+
1,
#3770
0)
#3772
1.
#3774
b100 3
b10110111 1
1*
#3780
0-
1+
0,
#3782
0*
#3790
b101 3
b1011011 1
1)
#3792
0.
#3800
1-
0+
1,
#3810
0)
#3812
1.
#3814
b110 3
b100001011 1
1*
#3820
0-
1+
0,
#3822
0*
#3830
b111 3
b10000101 1
1)
#3832
0.
#3840
1-
0+
1,
#3850
0)
#3852
1.
#3854
b1000 3
b100110101 1
1*
#3860
0-
1+
0,
#3862
0*
#3870
1!
b1001 3
b10011010 1
1)
#3872
0.
#3880
1-
0+
1,
#3890
0)
#3892
1.
#3894
0!
b0 3
1*
#3900
0-
1+
0,
#3902
0*
#3910
b1 3
b1110 1
1)
#3912
0.
#3920
1-
0+
1,
#3930
0)
#3932
1.
#3934
b11 3
b111 1
1*
#3940
0-
1+
0,
#3942
0*
#3950
b100 3
b10110111 1
1)
#3952
0.
#3960
1-
0+
1,
#3970
0)
#3972
1.
#3974
b101 3
b1011011 1
1*
#3980
0-
1+
0,
#3982
0*
#3990
b110 3
b100001011 1
1)
#3992
0.
#4000
1-
0+
1,
#4010
0)
#4012
1.
#4014
b111 3
b10000101 1
1*
#4020
0-
1+
0,
#4022
0*
#4030
b1000 3
b100110101 1
1)
#4032
0.
#4040
1-
0+
1,
#4050
0)
#4052
1.
#4054
1!
b1001 3
b10011010 1
1*
#4060
0-
1+
0,
#4062
0*
#4070
0!
b0 3
1)
#4072
0.
#4080
1-
0+
1,
#4090
0)
#4092
1.
#4094
b1 3
b1110 1
1*
#4100
0-
1+
0,
#4102
0*
#4110
b11 3
b111 1
1)
#4112
0.
#4120
1-
0+
1,
#4130
0)
#4132
1.
#4134
b100 3
b10110111 1
1*
#4140
0-
1+
0,
#4142
0*
#4150
b101 3
b1011011 1
1)
#4152
0.
#4160
1-
0+
1,
#4170
0)
#4172
1.
#4174
b110 3
b100001011 1
1*
#4180
0-
1+
0,
#4182
0*
#4190
b111 3
b10000101 1
1)
#4192
0.
#4200
1-
0+
1,
#4210
0)
#4212
1.
#4214
b1000 3
b100110101 1
1*
#4220
0-
1+
0,
#4222
0*
#4230
1!
b1001 3
b10011010 1
1)
#4232
0.
#4240
1-
0+
1,
#4250
0)
#4252
1.
#4254
0!
b0 3
1*
#4260
0-
1+
0,
#4262
0*
#4270
b1 3
b1110 1
1)
#4272
0.
#4280
1-
0+
1,
#4290
0)
#4292
1.
#4294
b11 3
b111 1
1*
#4300
0-
1+
0,
#4302
0*
#4310
b100 3
b10110111 1
1)
#4312
0.
#4320
1-
0+
1,
#4330
0)
#4332
1.
#4334
b101 3
b1011011 1
1*
#4340
0-
1+
0,
#4342
0*
#4350
b110 3
b100001011 1
1)
#4352
0.
#4360
1-
0+
1,
#4370
0)
#4372
1.
#4374
b111 3
b10000101 1
1*
#4380
0-
1+
0,
#4382
0*
#4390
b1000 3
b100110101 1
1)
#4392
0.
#4400
1-
0+
1,
#4410
0)
#4412
1.
#4414
1!
b1001 3
b10011010 1
1*
#4420
0-
1+
0,
#4422
0*
#4430
0!
b0 3
1)
#4432
0.
#4440
1-
0+
1,
#4450
0)
#4452
1.
#4454
b1 3
b1110 1
1*
#4460
0-
1+
0,
#4462
0*
#4470
b11 3
b111 1
1)
#4472
0.
#4480
1-
0+
1,
#4490
0)
#4492
1.
#4494
b100 3
b10110111 1
1*
#4500
0-
1+
0,
#4502
0*
#4510
b101 3
b1011011 1
1)
#4512
0.
#4520
1-
0+
1,
#4530
0)
#4532
1.
#4534
b110 3
b100001011 1
1*
#4540
0-
1+
0,
#4542
0*
#4550
b111 3
b10000101 1
1)
#4552
0.
#4560
1-
0+
1,
#4570
0)
#4572
1.
#4574
b1000 3
b100110101 1
1*
#4580
0-
1+
0,
#4582
0*
#4590
1!
b1001 3
b10011010 1
1)
#4592
0.
#4600
1-
0+
1,
#4610
0)
#4612
1.
#4614
0!
b0 3
1*
#4620
0-
1+
0,
#4622
0*
#4630
b1 3
b1110 1
1)
#4632
0.
#4640
1-
0+
1,
#4650
0)
#4652
1.
#4654
b11 3
b111 1
1*
#4660
0-
1+
0,
#4662
0*
#4670
b100 3
b10110111 1
1)
#4672
0.
#4680
1-
0+
1,
#4690
0)
#4692
1.
#4694
b101 3
b1011011 1
1*
#4700
0-
1+
0,
#4702
0*
#4710
b110 3
b100001011 1
1)
#4712
0.
#4720
1-
0+
1,
#4730
0)
#4732
1.
#4734
b111 3
b10000101 1
1*
#4740
0-
1+
0,
#4742
0*
#4750
b1000 3
b100110101 1
1)
#4752
0.
#4760
1-
0+
1,
#4770
0)
#4772
1.
#4774
1!
b1001 3
b10011010 1
1*
#4780
0-
1+
0,
#4782
0*
#4790
0!
b0 3
1)
#4792
0.
#4800
1-
0+
1,
#4810
0)
#4812
1.
#4814
b1 3
b1110 1
1*
#4820
0-
1+
0,
#4822
0*
#4830
b11 3
b111 1
1)
#4832
0.
#4840
1-
0+
1,
#4850
0)
#4852
1.
#4854
b100 3
b10110111 1
1*
#4860
0-
1+
0,
#4862
0*
#4870
b101 3
b1011011 1
1)
#4872
0.
#4880
1-
0+
1,
#4890
0)
#4892
1.
#4894
b110 3
b100001011 1
1*
#4900
0-
1+
0,
#4902
0*
#4910
b111 3
b10000101 1
1)
#4912
0.
#4920
1-
0+
1,
#4930
0)
#4932
1.
#4934
b1000 3
b100110101 1
1*
#4940
0-
1+
0,
#4942
0*
#4950
1!
b1001 3
b10011010 1
1)
#4952
0.
#4960
1-
0+
1,
#4970
0)
#4972
1.
#4974
0!
b0 3
1*
#4980
0-
1+
0,
#4982
0*
#4990
b1 3
b1110 1
1)
#4992
0.
#5000
1-
0+
1,
#5010
0)
#5012
1.
#5014
b11 3
b111 1
1*
#5020
0-
1+
0,
#5022
0*
#5030
b100 3
b10110111 1
1)
#5032
0.
#5040
1-
0+
1,
#5050
0)
#5052
1.
#5054
b101 3
b1011011 1
1*
#5060
0-
1+
0,
#5062
0*
#5070
b110 3
b100001011 1
1)
#5072
0.
#5080
1-
0+
1,
#5090
0)
#5092
1.
#5094
b111 3
b10000101 1
1*
#5100
0-
1+
0,
#5102
0*
#5110
b1000 3
b100110101 1
1)
#5112
0.
#5120
1-
0+
1,
#5130
0)
#5132
1.
#5134
1!
b1001 3
b10011010 1
1*
#5140
0-
1+
0,
#5142
0*
#5150
0!
b0 3
1)
#5152
0.
#5160
1-
0+
1,
#5170
0)
#5172
1.
#5174
b1 3
b1110 1
1*
#5180
0-
1+
0,
#5182
0*
#5190
b11 3
b111 1
1)
#5192
0.
#5200
1-
0+
1,
#5210
0)
#5212
1.
#5214
b100 3
b10110111 1
1*
#5220
0-
1+
0,
#5222
0*
#5230
b101 3
b1011011 1
1)
#5232
0.
#5240
1-
0+
1,
#5250
0)
#5252
1.
#5254
b110 3
b100001011 1
1*
#5260
0-
1+
0,
#5262
0*
#5270
b111 3
b10000101 1
1)
#5272
0.
#5280
1-
0+
1,
#5290
0)
#5292
1.
#5294
b1000 3
b100110101 1
1*
#5300
0-
1+
0,
#5302
0*
#5310
1!
b1001 3
b10011010 1
1)
#5312
0.
#5320
1-
0+
1,
#5330
0)
#5332
1.
#5334
0!
b0 3
1*
#5340
0-
1+
0,
#5342
0*
#5350
b1 3
b1110 1
1)
#5352
0.
#5360
1-
0+
1,
#5370
0)
#5372
1.
#5374
b11 3
b111 1
1*
#5380
0-
1+
0,
#5382
0*
#5390
b100 3
b10110111 1
1)
#5392
0.
#5400
1-
0+
1,
#5410
0)
#5412
1.
#5414
b101 3
b1011011 1
1*
#5420
0-
1+
0,
#5422
0*
#5430
b110 3
b100001011 1
1)
#5432
0.
#5440
1-
0+
1,
#5450
0)
#5452
1.
#5454
b111 3
b10000101 1
1*
#5460
0-
1+
0,
#5462
0*
#5470
b1000 3
b100110101 1
1)
#5472
0.
#5480
1-
0+
1,
#5490
0)
#5492
1.
#5494
1!
b1001 3
b10011010 1
1*
#5500
0-
1+
0,
#5502
0*
#5510
0!
b0 3
1)
#5512
0.
#5520
1-
0+
1,
#5530
0)
#5532
1.
#5534
b1 3
b1110 1
1*
#5540
0-
1+
0,
#5542
0*
#5550
b11 3
b111 1
1)
#5552
0.
#5560
1-
0+
1,
#5570
0)
#5572
1.
#5574
b100 3
b10110111 1
1*
#5580
0-
1+
0,
#5582
0*
#5590
b101 3
b1011011 1
1)
#5592
0.
#5600
1-
0+
1,
#5610
0)
#5612
1.
#5614
b110 3
b100001011 1
1*
#5620
0-
1+
0,
#5622
0*
#5630
b111 3
b10000101 1
1)
#5632
0.
#5640
1-
0+
1,
#5650
0)
#5652
1.
#5654
b1000 3
b100110101 1
1*
#5660
0-
1+
0,
#5662
0*
#5670
1!
b1001 3
b10011010 1
1)
#5672
0.
#5680
1-
0+
1,
#5690
0)
#5692
1.
#5694
0!
b0 3
1*
#5700
0-
1+
0,
#5702
0*
#5710
b1 3
b1110 1
1)
#5712
0.
#5720
1-
0+
1,
#5730
0)
#5732
1.
#5734
b11 3
b111 1
1*
#5740
0-
1+
0,
#5742
0*
#5750
b100 3
b10110111 1
1)
#5752
0.
#5760
1-
0+
1,
#5770
0)
#5772
1.
#5774
b101 3
b1011011 1
1*
#5780
0-
1+
0,
#5782
0*
#5790
b110 3
b100001011 1
1)
#5792
0.
#5800
1-
0+
1,
#5810
0)
#5812
1.
#5814
b111 3
b10000101 1
1*
#5820
0-
1+
0,
#5822
0*
#5830
b1000 3
b100110101 1
1)
#5832
0.
#5840
1-
0+
1,
#5850
0)
#5852
1.
#5854
1!
b1001 3
b10011010 1
1*
#5860
0-
1+
0,
#5862
0*
#5870
0!
b0 3
1)
#5872
0.
#5880
1-
0+
1,
#5890
0)
#5892
1.
#5894
b1 3
b1110 1
1*
#5900
0-
1+
0,
#5902
0*
#5910
b11 3
b111 1
1)
#5912
0.
#5920
1-
0+
1,
#5930
0)
#5932
1.
#5934
b100 3
b10110111 1
1*
#5940
0-
1+
0,
#5942
0*
#5950
b101 3
b1011011 1
1)
#5952
0.
#5960
1-
0+
1,
#5970
0)
#5972
1.
#5974
b110 3
b100001011 1
1*
#5980
0-
1+
0,
#5982
0*
#5990
b111 3
b10000101 1
1)
#5992
0.
#6000
1-
0+
1,
#6010
0)
#6012
1.
#6014
b1000 3
b100110101 1
1*
#6020
0-
1+
0,
#6022
0*
#6030
1!
b1001 3
b10011010 1
1)
#6032
0.
#6040
1-
0+
1,
#6050
0)
#6052
1.
#6054
0!
b0 3
1*
#6060
0-
1+
0,
#6062
0*
#6070
b1 3
b1110 1
1)
#6072
0.
#6080
1-
0+
1,
#6090
0)
#6092
1.
#6094
b11 3
b111 1
1*
#6100
0-
1+
0,
#6102
0*
#6110
b100 3
b10110111 1
1)
#6112
0.
#6120
1-
0+
1,
#6130
0)
#6132
1.
#6134
b101 3
b1011011 1
1*
#6140
0-
1+
0,
#6142
0*
#6150
b110 3
b100001011 1
1)
#6152
0.
#6160
1-
0+
1,
#6170
0)
#6172
1.
#6174
b111 3
b10000101 1
1*
#6180
0-
1+
0,
#6182
0*
#6190
b1000 3
b100110101 1
1)
#6192
0.
#6200
1-
0+
1,
#6210
0)
#6212
1.
#6214
1!
b1001 3
b10011010 1
1*
#6220
0-
1+
0,
#6222
0*
#6230
0!
b0 3
1)
#6232
0.
#6240
1-
0+
1,
#6250
0)
#6252
1.
#6254
b1 3
b1110 1
1*
#6260
0-
1+
0,
#6262
0*
#6270
b11 3
b111 1
1)
#6272
0.
#6280
1-
0+
1,
#6290
0)
#6292
1.
#6294
b100 3
b10110111 1
1*
#6300
0-
1+
0,
#6302
0*
#6310
b101 3
b1011011 1
1)
#6312
0.
#6320
1-
0+
1,
#6330
0)
#6332
1.
#6334
b110 3
b100001011 1
1*
#6340
0-
1+
0,
#6342
0*
#6350
b111 3
b10000101 1
1)
#6352
0.
